msgs/__init__.py
msgs/networkmsgs.py
msgs-1.0.2.dist-info/METADATA
msgs-1.0.2.dist-info/WHEEL
msgs-1.0.2.dist-info/entry_points.txt
msgs-1.0.2.dist-info/top_level.txt
msgs-1.0.2.dist-info/RECORD
