Metadata-Version: 2.1
Name: msgs
Version: 1.0.2
Summary: networkmsgs
Home-page: UNKNOWN
Author: liuzihao
License: UNKNOWN
Project-URL: Source Code, https://gitee.com/haozihan/msgs/tree/master/
Keywords: network msgs app
Platform: UNKNOWN
Requires-Python: >=3
